Metadata-Version: 1.0
Name: distributions-semihdesticioglu
Version: 0.1
Summary: Gaussian distributions
Home-page: UNKNOWN
Author: Semih Desticioglu
Author-email: desticioglu@gmail.com
License: UNKNOWN
Platform: UNKNOWN
